Workbook

Sheet Raw_Orders
A1: Order_ID | B1: Customer_ID | C1: Restaurant_ID | D1: Delivery_Partner_ID | E1: Order_Date | F1: Order_Value | G1: Status | H1: Delivery_Time_Min | I1: Customer_Rating
A2: 504897 | B2: CUST1333 | C2: REST296 | D2: DP317 | E2: 2024-04-06 | F2: 980.07 | G2: Delivered | H2: 28.6 | I2: 4.1
A3: 503302 | B3: CUST1109 | C3: REST274 | D3: DP490 | E3: 2024-04-12 | F3: 1123.98 | G3: Delivered | H3: 70.9 | I3: 2.8
A4: 501846 | B4: CUST1340 | C4: REST300 | D4: DP426 | E4: 2024-07-30 | F4: 125.1 | G4: Delivered | H4: 70.6 | I4: 4.6
A5: 500862 | B5: CUST1260 | C5: REST265 | D5: DP455 | E5: 2024-11-13 | F5: 227.97 | G5: Delivered | H5: 38.6 | I5: 2.9
A6: 501267 | B6: CUST1349 | C6: REST250 | D6: DP415 | E6: 2024-03-07 | F6: 700.67 | G6: Delivered | H6: 23.6 | I6: 4
A7: 500854 | B7: CUST1409 | C7: REST228 | D7: DP403 | E7: 2024-08-27 | F7: 293.42 | G7: Cancelled
A8: 504744 | B8: CUST1775 | C8: REST238 | D8: DP450 | E8: 2024-06-13 | F8: 372.71 | G8: Delivered | H8: 38.5 | I8: 4.1
A9: 502221 | B9: CUST1596 | C9: REST213 | D9: DP452 | E9: 2024-03-26 | F9: 753.82 | G9: Delivered | H9: 49 | I9: 4.2
A10: 502705 | B10: CUST1598 | C10: REST326 | D10: DP390 | E10: 2024-03-27 | F10: 1393.56 | G10: Delivered | H10: 51.6 | I10: 3.9
A11: 504378 | B11: CUST1714 | C11: REST283 | D11: DP434 | E11: 2024-05-27 | F11: 821.27 | G11: Delivered | H11: 70.9 | I11: 4.5
A12: 504759 | B12: CUST1151 | C12: REST294 | D12: DP328 | E12: 2024-07-31 | F12: -37.95 | G12: Delivered | H12: 46.9 | I12: 3.9
A13: 504487 | B13: CUST1410 | C13: REST330 | D13: DP408 | E13: 2024-09-21 | F13: 153.43 | G13: Delivered | H13: 22.2
A14: 504881 | B14: CUST1682 | C14: REST289 | D14: DP380 | E14: 2024-11-20 | F14: 291.68 | G14: Delivered | H14: 38 | I14: 2.9
A15: 501299 | B15: CUST1157 | C15: REST309 | D15: DP448 | E15: 2024-03-08 | F15: 461.03 | G15: Delivered | H15: 74.3 | I15: 3.4
A16: 502448 | B16: CUST1408 | C16: REST336 | D16: DP402 | E16: 2024-06-26 | F16: -51.51 | G16: Delivered | H16: 51.3 | I16: 3.2
A17: 504399 | B17: CUST1635 | C17: REST301 | D17: DP430 | E17: 2024-10-17 | F17: 569.22 | G17: Delivered | H17: 48.3 | I17: 3.6
A18: 504693 | B18: CUST1567 | C18: REST251 | D18: DP436 | E18: 2024-11-28 | F18: 1373.59 | G18: Delivered | H18: 18.2 | I18: 3.1
A19: 504233 | B19: CUST1310 | C19: REST208 | D19: DP336 | E19: 2024-12-23 | F19: 1294.2 | G19: Delivered | H19: 70 | I19: 2.8
A20: 500262 | B20: CUST1385 | C20: REST226 | D20: DP325 | E20: 2024-04-17 | F20: 578 | G20: Delivered | H20: 40.4 | I20: 2.6
A21: 503038 | B21: CUST1461 | C21: REST266 | D21: DP318 | E21: 2024-05-01 | F21: 1159.42 | G21: Cancelled
A22: 502350 | B22: CUST1578 | C22: REST276 | D22: DP493 | E22: 2024-11-04 | F22: 900.17 | G22: Delivered | H22: 57.6 | I22: 3.3
A23: 503448 | B23: CUST1469 | C23: REST341 | D23: DP390 | E23: 2024-03-16 | F23: 1013.68 | G23: Delivered | H23: 19.5
A24: 501391 | B24: CUST1118 | C24: REST269 | D24: DP315 | E24: 2024-02-01 | F24: 808.22 | G24: Delivered | H24: 75.1 | I24: 4.4
A25: 501198 | B25: CUST1348 | C25: REST330 | D25: DP376 | E25: 2024-12-11 | F25: 969.16 | G25: Cancelled
A26: 503657 | B26: CUST1732 | C26: REST207 | D26: DP450 | E26: 2024-06-13 | F26: 509.12 | G26: Delivered | H26: 69.8 | I26: 3.2
A27: 504650 | B27: CUST1173 | C27: REST338 | D27: DP337 | E27: 2024-12-11 | F27: 594.01 | G27: Delivered | H27: 41.2 | I27: 4
A28: 500338 | B28: CUST1426 | C28: REST257 | D28: DP419 | E28: 2024-11-30 | F28: 1146.44 | G28: Delivered | H28: 30.4 | I28: 4
A29: 502375 | B29: CUST1416 | C29: REST294 | D29: DP473 | E29: 2024-02-27 | F29: 530.3 | G29: Delayed | H29: 39.4
A30: 504967 | B30: CUST1258 | C30: REST224 | D30: DP323 | E30: 2024-05-17 | F30: 257.3 | G30: Delivered | H30: 39.5 | I30: 4.6
A31: 502866 | B31: CUST1425 | C31: REST240 | D31: DP330 | E31: 2024-01-04 | F31: 535.91 | G31: Delivered | H31: 49.9
A32: 500773 | B32: CUST1416 | C32: REST284 | D32: DP425 | E32: 2024-01-27 | F32: 800.21 | G32: Delivered | H32: 61.6 | I32: 3.7
A33: 503046 | B33: CUST1469 | C33: REST341 | D33: DP391 | E33: 2024-10-11 | F33: 722.99 | G33: Cancelled
A34: 504002 | B34: CUST1469 | C34: REST320 | D34: DP480 | E34: 2024-09-27 | F34: 799.72 | G34: Delivered | H34: 67.9 | I34: 2.8
A35: 502694 | B35: CUST1694 | C35: REST287 | D35: DP349 | E35: 2024-10-28 | F35: 148.92 | G35: Delivered | H35: 34.6 | I35: 4.1
A36: 504246 | B36: CUST1370 | C36: REST343 | D36: DP364 | E36: 2024-01-18 | F36: 1013.02 | G36: Delivered | H36: 15.9 | I36: 4.6
A37: 503625 | B37: CUST1001 | C37: REST336 | D37: DP353 | E37: 2024-09-27 | F37: 351.11 | G37: Cancelled
A38: 502565 | B38: CUST1767 | C38: REST243 | D38: DP403 | E38: 2024-12-16 | F38: 329.68 | G38: Cancelled
A39: 502811 | B39: CUST1087 | C39: REST328 | D39: DP450 | E39: 2024-07-04 | F39: 722.46 | G39: Delivered | H39: 45.2 | I39: 3.6
A40: 503316 | B40: CUST1184 | C40: REST243 | D40: DP449 | E40: 2024-06-28 | F40: 795.45 | G40: Delivered | H40: 72.7 | I40: 3.4
A41: 502860 | B41: CUST1211 | C41: REST239 | D41: DP430 | E41: 2024-10-21 | F41: 1305.01 | G41: Delivered | H41: 48.4 | I41: 3.1
A42: 500077 | B42: CUST1485 | C42: REST263 | D42: DP316 | E42: 2024-04-19 | F42: 396.35 | G42: Delivered | H42: 55.6
A43: 500774 | B43: CUST1223 | C43: REST305 | D43: DP444 | E43: 2024-03-03 | F43: 1094.75 | G43: Delivered | H43: 38.8 | I43: 4.2
A44: 502256 | B44: CUST1038 | C44: REST304 | D44: DP320 | E44: 2024-10-13 | F44: 488.43 | G44: Delayed | H44: 31.5
A45: 501356 | B45: CUST1419 | C45: REST282 | D45: DP494 | E45: 2024-08-31 | F45: 777.43 | G45: Delivered | H45: 69.6 | I45: 2.6
A46: 501300 | B46: CUST1367 | C46: REST293 | D46: DP456 | E46: 2024-12-06 | F46: 1179.47 | G46: Cancelled
A47: 501161 | B47: CUST1773 | C47: REST291 | D47: DP452 | E47: 2024-01-01 | F47: 197.81 | G47: Delivered | H47: 39.9 | I47: 3.4
A48: 503960 | B48: CUST1262 | C48: REST270 | D48: DP400 | E48: 2024-02-01 | F48: 371.88 | G48: Delivered | H48: 34.1 | I48: 4.1
A49: 502446 | B49: CUST1391 | C49: REST349 | D49: DP333 | E49: 2024-11-04 | F49: 529.01 | G49: Delivered | H49: 33.1 | I49: 2.7
A50: 503762 | B50: CUST1578 | C50: REST299 | D50: DP334 | E50: 2024-02-15 | F50: 1238.51 | G50: Delayed | H50: 62.7
A51: 500143 | B51: CUST1632 | C51: REST327 | D51: DP367 | E51: 2024-05-29 | F51: 1342.83 | G51: Delivered | H51: 35.5 | I51: 4.7
A52: 504782 | B52: CUST1166 | C52: REST219 | D52: DP343 | E52: 2024-06-15 | F52: 578.35 | G52: Delivered | H52: 25.1 | I52: 3.9
A53: 504610 | B53: CUST1561 | C53: REST245 | D53: DP313 | E53: 2024-11-13 | F53: 743.94 | G53: Delivered | H53: 16.1 | I53: 3.1
A54: 501058 | B54: CUST1301 | C54: REST211 | D54: DP439 | E54: 2024-01-06 | F54: 346.86 | G54: Cancelled
A55: 502326 | B55: CUST1339 | C55: REST276 | D55: DP465 | E55: 2024-10-18 | F55: 331.96 | G55: Delivered | H55: 42.2 | I55: 4.1
A56: 503086 | B56: CUST1322 | C56: REST345 | D56: DP470 | E56: 2024-05-24 | F56: 1097.23 | G56: Delivered | H56: 63.1 | I56: 4.4
A57: 501411 | B57: CUST1192 | C57: REST202 | D57: DP428 | E57: 2024-03-21 | F57: 431.56 | G57: Delivered | H57: 58.9 | I57: 4.2
A58: 503799 | B58: CUST1387 | C58: REST222 | D58: DP364 | E58: 2024-06-26 | F58: 286.35 | G58: Delivered | H58: 36.3 | I58: 3.9
A59: 504680 | B59: CUST1553 | C59: REST317 | D59: DP470 | E59: 2024-05-17 | F59: 1151.51 | G59: Delivered | H59: 55.3 | I59: 2.7
A60: 500909 | B60: CUST1525 | C60: REST329 | D60: DP377 | E60: 2024-02-02 | F60: 1382.91 | G60: Delivered | H60: 66.3 | I60: 4.1
A61: 501678 | B61: CUST1600 | C61: REST239 | D61: DP430 | E61: 2024-09-10 | F61: 857.73 | G61: Delivered | H61: 18.8 | I61: 2.7
A62: 500998 | B62: CUST1749 | C62: REST204 | D62: DP383 | E62: 2024-08-30 | F62: 217.98 | G62: Delivered | H62: 68.9
A63: 500607 | B63: CUST1150 | C63: REST280 | D63: DP361 | E63: 2024-09-05 | F63: 562.2 | G63: Delivered | H63: 33.4 | I63: 2.6
A64: 503006 | B64: CUST1312 | C64: REST266 | D64: DP380 | E64: 2024-01-02 | F64: 457.17 | G64: Delivered
A65: 502631 | B65: CUST1096 | C65: REST340 | D65: DP409 | E65: 2024-05-24 | F65: 793.9 | G65: Delivered | H65: 61.9 | I65: 4.8
A66: 500048 | B66: CUST1509 | C66: REST272 | D66: DP344 | E66: 2024-06-21 | F66: 1375.43 | G66: Delivered | H66: 75.9 | I66: 2.6
A67: 500175 | B67: CUST1729 | C67: REST327 | D67: DP476 | E67: 2024-06-08 | F67: 382.96 | G67: Delivered | H67: 76.8 | I67: 4.3
A68: 500706 | B68: CUST1173 | C68: REST299 | D68: DP463 | E68: 2024-03-11 | F68: 508.93 | G68: Delivered | H68: 32.9 | I68: 4.1
A69: 500512 | B69: CUST1393 | C69: REST347 | D69: DP325 | E69: 2024-12-23 | F69: 1390.63 | G69: Delivered | I69: 4.8
A70: 502135 | B70: CUST1496 | C70: REST213 | D70: DP365 | E70: 2024-06-16 | F70: 1028.12 | G70: Delivered | H70: 24.6 | I70: 3
A71: 501665 | B71: CUST1135 | C71: REST303 | D71: DP429 | E71: 2024-03-12 | F71: 639.82 | G71: Delivered | H71: 34.8
A72: 502182 | B72: CUST1501 | C72: REST230 | D72: DP354 | E72: 2024-01-11 | F72: 529.04 | G72: Delayed | H72: 39.1
A73: 502892 | B73: CUST1056 | C73: REST350 | D73: DP333 | E73: 2024-01-10 | F73: 1130.13 | G73: Delivered | H73: 49.9
A74: 502621 | B74: CUST1768 | C74: REST214 | D74: DP477 | E74: 2024-03-04 | F74: 1294 | G74: Delivered | I74: 3.9
A75: 502240 | B75: CUST1601 | C75: REST345 | D75: DP370 | E75: 2024-12-01 | F75: 597.63 | G75: Delivered | H75: 54.7 | I75: 4.1
A76: 501287 | B76: CUST1070 | C76: REST214 | D76: DP383 | E76: 2024-12-12 | F76: 205.45 | G76: Delayed | H76: 61.1
A77: 504719 | B77: CUST1615 | C77: REST346 | D77: DP469 | E77: 2024-03-21 | F77: 684.88 | G77: Delayed | H77: 33.1 | I77: 4
A78: 500778 | B78: CUST1681 | C78: REST308 | D78: DP423 | E78: 2024-11-08 | F78: 580.18 | G78: Delivered | H78: 52.3 | I78: 2.9
A79: 500326 | B79: CUST1523 | C79: REST205 | D79: DP384 | E79: 2024-10-24 | F79: 1020 | G79: Delivered | H79: 25.3 | I79: 4.1
A80: 503976 | B80: CUST1205 | C80: REST349 | D80: DP361 | E80: 2024-04-02 | F80: 1244.1 | G80: Delivered | H80: 75.8 | I80: 4.3
A81: 504699 | B81: CUST1619 | C81: REST346 | D81: DP470 | E81: 2024-04-04 | F81: 781.8 | G81: Cancelled
A82: 503338 | B82: CUST1701 | C82: REST277 | D82: DP345 | E82: 2024-02-25 | F82: 933.04 | G82: Delivered | H82: 67.2 | I82: 3.6
A83: 500146 | B83: CUST1247 | C83: REST330 | D83: DP487 | E83: 2024-06-12 | F83: 1390.43 | G83: Delivered | H83: 31.2 | I83: 2.5
A84: 502107 | B84: CUST1232 | C84: REST339 | D84: DP339 | E84: 2024-01-12 | F84: 375.93 | G84: Delivered | H84: 41.4
A85: 504480 | B85: CUST1125 | C85: REST336 | D85: DP375 | E85: 2024-12-26 | F85: 826.94 | G85: Cancelled
A86: 504954 | B86: CUST1330 | C86: REST346 | D86: DP357 | E86: 2024-05-22 | F86: 454.78 | G86: Delivered | H86: 15.9 | I86: 4.5
A87: 500385 | B87: CUST1716 | C87: REST288 | D87: DP453 | E87: 2024-11-21 | F87: 171.17 | G87: Delivered | H87: 47.1 | I87: 4.1
A88: 503781 | B88: CUST1503 | C88: REST336 | D88: DP313 | E88: 2024-12-04 | F88: 1398.36 | G88: Delivered | H88: 79.8
A89: 502401 | B89: CUST1250 | C89: REST214 | D89: DP406 | E89: 2024-06-18 | F89: 688.82 | G89: Cancelled
A90: 504949 | B90: CUST1735 | C90: REST254 | D90: DP373 | E90: 2024-12-14 | F90: 561.41 | G90: Delivered | H90: 75.9
A91: 502572 | B91: CUST1236 | C91: REST349 | D91: DP307 | E91: 2024-02-24 | F91: 305.04 | G91: Delivered | H91: 28 | I91: 4.5
A92: 504060 | B92: CUST1309 | C92: REST318 | D92: DP422 | E92: 2024-08-25 | F92: 1140.67 | G92: Delivered | H92: 28 | I92: 2.6
A93: 502158 | B93: CUST1495 | C93: REST337 | D93: DP386 | E93: 2024-05-29 | F93: 808.18 | G93: Delivered | H93: 38.4 | I93: 2.7
A94: 503074 | B94: CUST1355 | C94: REST212 | D94: DP474 | E94: 2024-12-21 | F94: 474.81 | G94: Delivered | H94: 79.5 | I94: 3.7
A95: 500229 | B95: CUST1339 | C95: REST312 | D95: DP494 | E95: 2024-03-08 | F95: 606.14 | G95: Delivered | H95: 28.3 | I95: 4.8
A96: 503437 | B96: CUST1394 | C96: REST336 | D96: DP314 | E96: 2024-01-06 | F96: 803.12 | G96: Cancelled
A97: 503642 | B97: CUST1485 | C97: REST309 | D97: DP317 | E97: 2024-08-20 | F97: 1267.15 | G97: Delivered | I97: 3
A98: 504740 | B98: CUST1561 | C98: REST224 | D98: DP418 | E98: 2024-09-17 | F98: 705.71 | G98: Delivered | H98: 16.9 | I98: 2.5
A99: 500005 | B99: CUST1612 | C99: REST245 | D99: DP457 | E99: 2024-05-15 | F99: 123.04 | G99: Delivered | H99: 19.5 | I99: 3
A100: 503891 | B100: CUST1731 | C100: REST299 | D100: DP329 | E100: 2024-05-18 | F100: 502.91 | G100: Delayed | H100: 37.1
...

Sheet Raw_Customers
A1: Customer_ID | B1: Customer_Name | C1: City | D1: Signup_Date | E1: Age | F1: Gender
A2: CUST1001 | B2: Ananya Patel | C2: Hyderabad | D2: 2023-02-19 | E2: 22
A3: CUST1002 | B3: Vivaan Joshi | C3: Delhi | D3: 2023-02-08 | E3: 23 | F3: Female
A4: CUST1003 | B4: Ayaan Verma | C4: KOLKATA | D4: 2024-03-10 | E4: 21
A5: CUST1004 | B5: Riya Sharma | C5: JAIPUR | D5: 2024-02-11 | E5: 21 | F5: Female
A6: CUST1005 | B6: Ishaan Yadav | C6: Mumbai | D6: 2023-05-01 | E6: 54 | F6: Male
A7: CUST1006 | B7: Sai Verma | C7: Jaipur | D7: 2023-07-12 | E7: 41 | F7: Male
A8: CUST1007 | B8: Aditya Reddy | C8: Bhopal | D8: 2023-07-30 | E8: 49
A9: CUST1008 | B9: Ananya Mishra | C9: Jaipur | D9: 2024-04-09 | E9: 41 | F9: Male
A10: CUST1009 | B10: Sai Singh | C10: Indore | D10: 2023-11-04 | E10: 51 | F10: Female
A11: CUST1010 | B11: Kiara Gupta | C11: Jaipur | D11: 2023-03-16 | E11: 25
A12: CUST1011 | B12: Ananya Patel | C12: Chennai | D12: 2024-03-07 | E12: 20 | F12: Male
A13: CUST1012 | B13: Riya Kumar | C13: Pune | D13: 2023-12-25 | E13: 49
A14: CUST1013 | B14: Aditya Verma | C14: Bangalore | D14: 2024-04-30 | E14: 22 | F14: Male
A15: CUST1014 | B15: Ishaan Reddy | C15: Chennai | D15: 2023-10-19 | E15: 42 | F15: Male
A16: CUST1015 | B16: Diya Patel | C16: Jaipur | D16: 2023-04-30 | E16: 49 | F16: Male
A17: CUST1016 | B17: Ishaan Patel | C17: Delhi | D17: 2024-02-12 | E17: 43 | F17: Female
A18: CUST1017 | B18: Saanvi Joshi | C18: Bangalore | D18: 2023-05-21 | E18: 45
A19: CUST1018 | B19: Aadhya Kumar | C19: Hyderabad | D19: 2023-08-25 | E19: 27 | F19: Male
A20: CUST1019 | B20: Ayaan Singh | C20: Bhopal | D20: 2024-05-11 | E20: 55 | F20: Female
A21: CUST1020 | B21: Aarav Patel | C21: Hyderabad | D21: 2024-01-14 | E21: 54 | F21: Male
A22: CUST1021 | B22: Anika Reddy | C22: Bhopal | D22: 2024-04-12 | E22: 53 | F22: Female
A23: CUST1022 | B23: Saanvi Verma | C23: CHENNAI | D23: 2024-02-15 | E23: 21 | F23: Female
A24: CUST1023 | B24: Kiara Patel | C24: INDORE | D24: 2023-12-15 | E24: 21 | F24: Male
A25: CUST1024 | B25: Navya Verma | C25: Pune | D25: 2023-01-27 | E25: 22 | F25: Female
A26: CUST1025 | B26: Arjun Gupta | C26: Pune | D26: 2024-01-08 | E26: 48 | F26: Male
A27: CUST1026 | B27: Kiara Mishra | C27: chennai | D27: 2023-11-16 | E27: 23 | F27: Female
A28: CUST1027 | B28: Krishna Mishra | C28: Mumbai | D28: 2024-06-12 | E28: 19 | F28: Female
A29: CUST1028 | B29: Anika Kumar | C29: Mumbai | D29: 2023-01-28 | E29: 51 | F29: Male
A30: CUST1029 | B30: Aditya Gupta | C30: Kolkata | D30: 2024-01-11 | E30: 28 | F30: Male
A31: CUST1030 | B31: Navya Joshi | C31: Kolkata | D31: 2023-12-04 | E31: 32
A32: CUST1031 | B32: Reyansh Singh | C32: Hyderabad | D32: 2023-08-21 | E32: 30
A33: CUST1032 | B33: Aarav Sharma | C33: Bangalore | D33: 2024-04-28 | E33: 34 | F33: Female
A34: CUST1033 | B34: Diya Mishra | C34: Pune | D34: 2024-01-09 | E34: 23 | F34: Female
A35: CUST1034 | B35: Reyansh Kumar | C35: Delhi | D35: 2024-05-09 | E35: 18 | F35: Female
A36: CUST1035 | B36: Diya Verma | C36: Indore | D36: 2024-02-02 | E36: 30 | F36: Female
A37: CUST1036 | B37: Aadhya Kumar | C37: Indore | D37: 2024-02-10 | E37: 47 | F37: Female
A38: CUST1037 | B38: Aditya Patel | C38: Mumbai | D38: 2023-05-11 | E38: 19 | F38: Female
A39: CUST1038 | B39: Kiara Patel | C39: Jaipur | D39: 2024-04-30 | E39: 40 | F39: Female
A40: CUST1039 | B40: Arjun Sharma | C40: Bhopal | D40: 2023-04-16 | E40: 51 | F40: Female
A41: CUST1040 | B41: Reyansh Singh | C41: Bhopal | D41: 2023-09-15 | E41: 31 | F41: Male
A42: CUST1041 | B42: Riya Kumar | C42: Bangalore | D42: 2024-03-05 | E42: 26 | F42: Male
A43: CUST1042 | B43: Diya Mishra | C43: JAIPUR | D43: 2024-06-13 | E43: 44
A44: CUST1043 | B44: Anika Joshi | C44: BHOPAL | D44: 2024-03-26 | E44: 29
A45: CUST1044 | B45: Sai Patel | C45: Chennai | D45: 2023-05-04 | E45: 53 | F45: Male
A46: CUST1045 | B46: Anika Joshi | C46: KOLKATA | D46: 2024-05-09 | E46: 24
A47: CUST1046 | B47: Krishna Sharma | C47: Indore | D47: 2024-06-03 | E47: 46
A48: CUST1047 | B48: Kiara Kumar | C48: Jaipur | D48: 2024-06-01 | E48: 50 | F48: Female
A49: CUST1048 | B49: Kiara Joshi | C49: Kolkata | D49: 2024-05-04 | E49: 50 | F49: Female
A50: CUST1049 | B50: Krishna Joshi | C50: Delhi | D50: 2024-04-03 | E50: 26 | F50: Female
A51: CUST1050 | B51: Ananya Verma | C51: Delhi | D51: 2024-03-14 | E51: 22 | F51: Female
A52: CUST1051 | B52: Vihaan Patel | C52: Pune | D52: 2023-05-27 | E52: 34 | F52: Female
A53: CUST1052 | B53: Ayaan Verma | C53: Hyderabad | D53: 2024-05-13 | E53: 28 | F53: Female
A54: CUST1053 | B54: Aadhya Joshi | C54: Hyderabad | D54: 2023-12-14 | E54: 44 | F54: Female
A55: CUST1054 | B55: Aditya Kumar | C55: Bhopal | D55: 2023-12-13 | E55: 53 | F55: Female
A56: CUST1055 | B56: Aarav Yadav | C56: Pune | D56: 2024-06-13 | E56: 36
A57: CUST1056 | B57: Vihaan Singh | C57: INDORE | D57: 2023-03-28 | E57: 34 | F57: Male
A58: CUST1057 | B58: Krishna Patel | C58: Hyderabad | D58: 2023-09-22 | E58: 43 | F58: Female
A59: CUST1058 | B59: Anika Reddy | C59: CHENNAI | D59: 2023-12-01 | E59: 23 | F59: Male
A60: CUST1059 | B60: Aadhya Verma | C60: BANGALORE | D60: 2023-01-18 | E60: 23 | F60: Male
A61: CUST1060 | B61: Aditya Gupta | C61: Indore | D61: 2024-04-09 | E61: 18 | F61: Male
A62: CUST1061 | B62: Aadhya Gupta | C62: Jaipur | D62: 2023-05-13 | E62: 20
A63: CUST1062 | B63: Vihaan Patel | C63: Bangalore | D63: 2023-02-21 | E63: 29 | F63: Female
A64: CUST1063 | B64: Ishaan Joshi | C64: Delhi | D64: 2023-10-24 | E64: 46
A65: CUST1064 | B65: Krishna Kumar | C65: Bhopal | D65: 2023-09-14 | E65: 20 | F65: Male
A66: CUST1065 | B66: Navya Singh | C66: Kolkata | D66: 2024-05-01 | E66: 33 | F66: Female
A67: CUST1066 | B67: Myra Joshi | C67: Hyderabad | D67: 2024-06-02 | E67: 37 | F67: Female
A68: CUST1067 | B68: Ananya Singh | C68: Mumbai | D68: 2024-02-19 | E68: 40 | F68: Male
A69: CUST1068 | B69: Aarav Verma | C69: Bangalore | D69: 2024-03-17 | E69: 28 | F69: Male
A70: CUST1069 | B70: Anika Gupta | C70: Jaipur | D70: 2023-09-06 | E70: 36 | F70: Male
A71: CUST1070 | B71: Sai Gupta | C71: Chennai | D71: 2023-01-04 | E71: 34 | F71: Male
A72: CUST1071 | B72: Navya Kumar | C72: Delhi | D72: 2023-02-05 | E72: 37 | F72: Female
A73: CUST1072 | B73: Aarav Kumar | C73: Hyderabad | D73: 2023-03-27 | E73: 48 | F73: Male
A74: CUST1073 | B74: Reyansh Singh | C74: Kolkata | D74: 2023-01-06 | E74: 23 | F74: Male
A75: CUST1074 | B75: Arjun Yadav | C75: Jaipur | D75: 2023-02-12 | E75: 43 | F75: Male
A76: CUST1075 | B76: Ayaan Verma | C76: Jaipur | D76: 2024-06-25 | E76: 27
A77: CUST1076 | B77: Ananya Mishra | C77: Mumbai | D77: 2023-10-18 | E77: 27 | F77: Male
A78: CUST1077 | B78: Anika Yadav | C78: Kolkata | D78: 2023-05-23 | E78: 51
A79: CUST1078 | B79: Aarav Reddy | C79: delhi | D79: 2023-03-29 | E79: 19 | F79: Male
A80: CUST1079 | B80: Vihaan Yadav | C80: Chennai | D80: 2023-02-21 | E80: 19
A81: CUST1080 | B81: Myra Gupta | C81: Bhopal | D81: 2024-04-12 | E81: 22
A82: CUST1081 | B82: Aditya Joshi | C82: Indore | D82: 2024-04-30 | E82: 34 | F82: Male
A83: CUST1082 | B83: Ayaan Singh | C83: delhi | D83: 2024-04-16 | E83: 49 | F83: Female
A84: CUST1083 | B84: Vivaan Reddy | C84: Delhi | D84: 2023-03-21 | E84: 27 | F84: Male
A85: CUST1084 | B85: Ishaan Reddy | C85: jaipur | D85: 2023-05-17 | E85: 18 | F85: Female
A86: CUST1085 | B86: Vihaan Singh | C86: Chennai | D86: 2023-10-25 | E86: 51 | F86: Male
A87: CUST1086 | B87: Kiara Verma | C87: Kolkata | D87: 2023-07-24 | E87: 37 | F87: Male
A88: CUST1087 | B88: Aarav Gupta | C88: Chennai | D88: 2023-03-20 | E88: 50 | F88: Female
A89: CUST1088 | B89: Saanvi Singh | C89: Delhi | D89: 2023-03-18 | E89: 55 | F89: Male
A90: CUST1089 | B90: Krishna Kumar | C90: Mumbai | D90: 2024-06-04 | E90: 35 | F90: Male
A91: CUST1090 | B91: Ayaan Mishra | C91: Chennai | D91: 2024-02-08 | E91: 19 | F91: Female
A92: CUST1091 | B92: Kiara Yadav | C92: Bangalore | D92: 2023-05-25 | E92: 44 | F92: Male
A93: CUST1092 | B93: Vihaan Kumar | C93: BHOPAL | D93: 2023-11-29 | E93: 39 | F93: Female
... A96: CUST1095 | B96: Vivaan Gupta | C96: Mumbai | D96: 2023-09-13 | E96: 35 | F96: Female
A97: CUST1096 | B97: Reyansh Kumar | C97: Hyderabad | D97: 2023-01-30 | E97: 43
A98: CUST1097 | B98: Aditya Sharma | C98: Hyderabad | D98: 2024-04-06 | E98: 26 | F98: Male
A99: CUST1098 | B99: Navya Patel | C99: Mumbai | D99: 2024-04-28 | E99: 44 | F99: Male
A100: CUST1099 | B100: Krishna Gupta | C100: Hyderabad | D100: 2023-09-02 | E100: 37 | F100: Female
A101: CUST1100 | B101: Saanvi Verma | C101: Mumbai | D101: 2023-06-15 | E101: 22 | F101: Female
A102: CUST1101 | B102: Myra Joshi | C102: Delhi | D102: 2024-04-08 | E102: 39 | F102: Female
...

Sheet Raw_Restaurants
A1: Restaurant_ID | B1: Restaurant_Name | C1: City | D1: Category | E1: Avg_Cost_For_Two | F1: Rating | G1: Onboard_Date
A2: REST201 | B2: Kolkata Zone 1 | C2: Kolkata | D2: Desserts | E2: 500 | F2: 4.4 | G2: 2023-12-21
A3: REST202 | B3: Bangalore Treats 2 | C3: Bangalore | D3: Beverages | E3: 400 | F3: 3.6 | G3: 2023-12-24
A4: REST203 | B4: Chennai Kitchen 3 | C4: Chennai | D4: North Indian | E4: 250 | F4: 4.5 | G4: 2023-06-01
A5: REST204 | B5: Bhopal Eats 4 | C5: Bhopal | D5: Continental | E5: 250 | F5: 3.5 | G5: 2023-07-12
A6: REST205 | B6: Delhi Plates 5 | C6: Delhi | D6: Continental | E6: 150 | F6: 3.7 | G6: 2023-01-14
A7: REST206 | B7: Indore Bites 6 | C7: Indore | D7: Continental | E7: 150 | F7: 3.3 | G7: 2023-11-04
A8: REST207 | B8: Chennai Bites 7 | C8: Chennai | D8: Beverages | E8: 350 | F8: 3.5 | G8: 2023-11-08
A9: REST208 | B9: Mumbai Junction 8 | C9: Mumbai | D9: Beverages | E9: 200 | F9: 4.2 | G9: 2023-09-14
A10: REST209 | B10: Bangalore House 9 | C10: Bangalore | D10: South Indian | E10: 250 | F10: 4.7 | G10: 2023-04-25
A11: REST210 | B11: Chennai Corner 10 | C11: Chennai | D11: Fast Food | E11: 350 | F11: 4.7 | G11: 2023-04-24
A12: REST211 | B12: Mumbai Eats 11 | C12: Mumbai | D12: Fast Food | E12: 200 | F12: 4.1 | G12: 2023-09-30
A13: REST212 | B13: Jaipur Treats 12 | C13: Jaipur | D13: South Indian | E13: 200 | F13: 3.7 | G13: 2023-08-29
... A151: REST350 | B151: Indore Plates 150 | C151: Indore | D151: Chinese | E151: 250 | F151: 3.3 | G151: 2023-06-03

Sheet Raw_DeliveryPartners
A1: Delivery_Partner_ID | B1: Partner_Name | C1: City | D1: Vehicle_Type | E1: Join_Date | F1: Partner_Rating
A2: DP301 | B2: Kiara Singh | C2: Pune | D2: Bike | E2: 2024-02-28 | F2: 3.2
A3: DP302 | B3: Ayaan Sharma | C3: Indore | D3: Bicycle | E3: 2023-04-21 | F3: 3.9
A4: DP303 | B4: Myra Sharma | C4: Delhi | D4: Bike | E4: 2023-12-26 | F4: 3.1
A5: DP304 | B5: Saanvi Yadav | C5: Kolkata | D5: Bicycle | E5: 2023-08-18 | F5: 3.6
A6: DP305 | B6: Aditya Reddy | C6: Kolkata | D6: Scooter | E6: 2024-03-27 | F6: 4.4
A7: DP306 | B7: Riya Joshi | C7: Chennai | D7: Bicycle | E7: 2023-07-02 | F7: 4.7
A8: DP307 | B8: Aadhya Singh | C8: Bhopal | D8: Scooter | E8: 2023-08-09 | F8: 3.9
A9: DP308 | B9: Riya Singh | C9: Kolkata | D9: Scooter | E9: 2023-05-02 | F9: 3.2
A10: DP309 | B10: Diya Yadav | C10: Bhopal | D10: Bike | E10: 2023-09-23 | F10: 4.3
A11: DP310 | B11: Sai Singh | C11: Chennai | D11: Bike | E11: 2023-11-04 | F11: 3.9
A12: DP311 | B12: Reyansh Patel | C12: Hyderabad | D12: Scooter | E12: 2023-01-03 | F12: 4.3
A13: DP312 | B13: Aarav Yadav | C13: Chennai | D13: Scooter | E13: 2023-11-29 | F13: 4
... A201: DP500 | B201: Anika Kumar | C201: Indore | D201: Bicycle | E201: 2023-01-20 | F201: 3.2

Sheet Raw_Payments
A1: Transaction_ID | B1: Order_ID | C1: Payment_Mode | D1: Amount | E1: Transaction_Status
A2: TXN700000 | B2: 504897 | C2: CASH | D2: 980.07 | E2: Success
A3: TXN700001 | B3: 503302 | C3: Cash | D3: 1123.98 | E3: Success
A4: TXN700002 | B4: 501846 | D4: 125.1 | E4: Success
A5: TXN700003 | B5: 500862 | C5: UPI | D5: 227.97 | E5: Success
A6: TXN700004 | B6: 501267 | D6: 700.67 | E6: Success
A7: TXN700005 | B7: 500854 | C7: Cash | D7: 293.42 | E7: Failed
A8: TXN700006 | B8: 504744 | C8: CASH | D8: 372.71 | E8: Success
A9: TXN700007 | B9: 502221 | C9: upi | D9: 753.82 | E9: Success
A10: TXN700008 | B10: 502705 | C10: UPI | D10: 1393.56 | E10: Success
A11: TXN700009 | B11: 504378 | C11: Credit Card | D11: 821.27 | E11: Success
A12: TXN700010 | B12: 504759 | C12: UPI | D12: -37.95 | E12: Failed
A13: TXN700011 | B13: 504487 | C13: upi | D13: 153.43 | E13: Failed
A14: TXN700012 | B14: 504881 | C14: CASH | D14: 291.68 | E14: Success
A15: TXN700013 | B15: 501299 | C15: CASH | D15: 461.03 | E15: Success
A16: TXN700014 | B16: 502448 | C16: Wallet | D16: -51.51 | E16: Success
A17: TXN700015 | B17: 504399 | C17: Wallet | D17: 569.22 | E17: Failed
A18: TXN700016 | B18: 504693 | C18: CASH | D18: 1373.59 | E18: Success
... A31: TXN700029 | B31: 502866 | C31: CASH | D31: 535.91 | E31: Success
A32: TXN700030 | B32: 500773 | D32: 800.21 | E32: Success
A33: TXN700031 | B33: 503046 | C33: upi | D33: 722.99 | E33: Refunded
A34: TXN700032 | B34: 504002 | C34: CASH | D34: 799.72 | E34: Pending
A35: TXN700033 | B35: 502694 | C35: upi | D35: 148.92 | E35: Success
A36: TXN700034 | B36: 504246 | C36: Wallet | D36: 1013.02 | E36: Success
A37: TXN700035 | B37: 503625 | C37: CASH | D37: 351.11 | E37: Failed
A38: TXN700036 | B38: 502565 | C38: Wallet | D38: 329.68 | E38: Refunded
A39: TXN700037 | B39: 502811 | C39: CASH | D39: 722.46 | E39: Success
A40: TXN700038 | B40: 503316 | C40: Cash | D40: 795.45 | E40: Success
A41: TXN700039 | B41: 502860 | C41: Credit Card | D41: 1305.01 | E41: Success
A42: TXN700040 | B42: 500077 | C42: CASH | D42: 396.35 | E42: Success
A43: TXN700041 | B43: 500774 | C43: Wallet | D43: 1094.75 | E43: Success
A44: TXN700042 | B44: 502256 | C44: Cash | D44: 488.43 | E44: Success
... A59: TXN700057 | B59: 504680 | C59: UPI | D59: 1151.51 | E59: Pending
A60: TXN700058 | B60: 500909 | D60: 1382.91 | E60: Success
A61: TXN700059 | B61: 501678 | C61: Credit Card | D61: 857.73 | E61: Pending
A62: TXN700060 | B62: 500998 | C62: Wallet | D62: 217.98 | E62: Failed
A63: TXN700061 | B63: 500607 | C63: CASH | D63: 562.2 | E63: Pending
A64: TXN700062 | B64: 503006 | C64: Cash | D64: 457.17 | E64: Success
A65: TXN700063 | B65: 502631 | C65: upi | D65: 793.9 | E65: Success
A66: TXN700064 | B66: 500048 | C66: Wallet | D66: 1375.43 | E66: Success
A67: TXN700065 | B67: 500175 | D67: 382.96 | E67: Success
A68: TXN700066 | B68: 500706 | D68: 508.93 | E68: Success
A69: TXN700067 | B69: 500512 | C69: Wallet | D69: 1390.63 | E69: Success
A70: TXN700068 | B70: 502135 | C70: CASH | D70: 1028.12 | E70: Success
A71: TXN700069 | B71: 501665 | C71: CASH | D71: 639.82 | E71: Success
A72: TXN700070 | B72: 502182 | C72: Cash | D72: 529.04 | E72: Success
A73: TXN700071 | B73: 502892 | C73: CASH | D73: 1130.13 | E73: Success
A74: TXN700072 | B74: 502621 | C74: Credit Card | D74: 1294 | E74: Success
A75: TXN700073 | B75: 502240 | C75: Credit Card | D75: 597.63 | E75: Failed
A76: TXN700074 | B76: 501287 | C76: Wallet | D76: 205.45 | E76: Success
A77: TXN700075 | B77: 504719 | C77: UPI | D77: 684.88 | E77: Success
A78: TXN700076 | B78: 500778 | D78: 580.18 | E78: Success
A79: TXN700077 | B79: 500326 | D79: 1020 | E79: Success
A80: TXN700078 | B80: 503976 | C80: UPI | D80: 1244.1 | E80: Failed
A81: TXN700079 | B81: 504699 | C81: CASH | D81: 781.8 | E81: Failed
A82: TXN700080 | B82: 503338 | D82: 933.04 | E82: Success
A83: TXN700081 | B83: 500146 | C83: UPI | D83: 1390.43 | E83: Pending
A84: TXN700082 | B84: 502107 | C84: UPI | D84: 375.93 | E84: Success
A85: TXN700083 | B85: 504480 | C85: Cash | D85: 826.94 | E85: Failed
A86: TXN700084 | B86: 504954 | C86: Debit Card | D86: 454.78 | E86: Success
A87: TXN700085 | B87: 500385 | C87: Credit Card | D87: 171.17 | E87: Success
A88: TXN700086 | B88: 503781 | C88: upi | D88: 1398.36 | E88: Success
A89: TXN700087 | B89: 502401 | C89: UPI | D89: 688.82 | E89: Failed
A90: TXN700088 | B90: 504949 | C90: CASH | D90: 561.41 | E90: Success
A91: TXN700089 | B91: 502572 | C91: Debit Card | D91: 305.04 | E91: Success
A92: TXN700090 | B92: 504060 | C92: CASH | D92: 1140.67 | E92: Success
A93: TXN700091 | B93: 502158 | C93: CASH | D93: 808.18 | E93: Success
A94: TXN700092 | B94: 503074 | C94: Debit Card | D94: 474.81 | E94: Success
... A101: TXN700099 | B101: 504367 | C101: Debit Card | D101: 1108.48 | E101: Success
A102: TXN700100 | B102: 503587 | D102: 1254.97 | E102: Success
A103: TXN700101 | B103: 501502 | C103: Wallet | D103: 686.8 | E103: Refunded
A104: TXN700102 | B104: 502897 | C104: CASH | D104: 675.58 | E104: Pending
A105: TXN700103 | B105: 504104 | C105: upi | D105: 555.94 | E105: Success
A106: TXN700104 | B106: 501552 | C106: CASH | D106: 901.59 | E106: Success
A107: TXN700105 | B107: 502898 | C107: Wallet | D107: 1043.24 | E107: Success
A108: TXN700106 | B108: 503882 | C108: Debit Card | D108: 409.98 | E108: Pending
A109: TXN700107 | B109: 501169 | C109: Wallet | D109: 987.72 | E109: Failed
A110: TXN700108 | B110: 502001 | C110: Wallet | D110: 739.57 | E110: Failed
A111: TXN700109 | B111: 504698 | C111: UPI | D111: 880.39 | E111: Refunded
A112: TXN700110 | B112: 503681 | C112: Debit Card | D112: 944.46 | E112: Success
A113: TXN700111 | B113: 504346 | C113: CASH | D113: 1124.84 | E113: Failed
A114: TXN700112 | B114: 500041 | C114: Debit Card | D114: 154.6 | E114: Success
A115: TXN700113 | B115: 504430 | C115: Wallet | D115: 701.29 | E115: Success
A116: TXN700114 | B116: 502022 | D116: 1303.99 | E116: Success
A117: TXN700115 | B117: 504476 | C117: Wallet | D117: 645.35 | E117: Failed
A118: TXN700116 | B118: 500956 | D118: 972.55 | E118: Success
A119: TXN700117 | B119: 502878 | C119: upi | D119: 1154.57 | E119: Success
A120: TXN700118 | B120: 501315 | C120: Credit Card | D120: 221.47 | E120: Success
A121: TXN700119 | B121: 501249 | C121: Debit Card | D121: 1090.36 | E121: Failed
A122: TXN700120 | B122: 501034 | C122: CASH | D122: 478.06 | E122: Success
A123: TXN700121 | B123: 504468 | C123: Debit Card | D123: 828.5 | E123: Success
A124: TXN700122 | B124: 502268 | C124: CASH | D124: 1086.1 | E124: Success
A125: TXN700123 | B125: 500228 | C125: upi | D125: 951.95 | E125: Success
A126: TXN700124 | B126: 501820 | C126: Debit Card | D126: 639.95 | E126: Success
A127: TXN700125 | B127: 503907 | C127: upi | D127: 1351.11 | E127: Success
A128: TXN700126 | B128: 504567 | D128: 853.59 | E128: Failed
A129: TXN700127 | B129: 504050 | C129: upi | D129: 438.51 | E129: Failed
A130: TXN700128 | B130: 501853 | C130: Debit Card | D130: 1080.73 | E130: Success
A131: TXN700129 | B131: 504212 | C131: upi | D131: 699.83 | E131: Success
A132: TXN700130 | B132: 502676 | D132: 164.54 | E132: Success
...

Sheet Cleaned_Customers
A1: Customer_ID | B1: Customer_Name | C1: City_Clean | D1: Signup_Date | E1: Age | F1: Gender_Clean
A2: =Raw_Customers!A2 -> CUST1001 | B2: =Raw_Customers!B2 -> Ananya Patel | C2: =PROPER(TRIM(Raw_Customers!C2)) -> Hyderabad | D2: =Raw_Customers!D2 -> 2023-02-19 | E2: =Raw_Customers!E2 -> 22 | F2: =IF(TRIM(Raw_Customers!F2)="","Not Specified",TRIM(Raw_Customers!F2)) -> Not Specified
A3: =Raw_Customers!A3 -> CUST1002 | B3: =Raw_Customers!B3 -> Vivaan Joshi | C3: =PROPER(TRIM(Raw_Customers!C3)) -> Delhi | D3: =Raw_Customers!D3 -> 2023-02-08 | E3: =Raw_Customers!E3 -> 23 | F3: =IF(TRIM(Raw_Customers!F3)="","Not Specified",TRIM(Raw_Customers!F3)) -> Female
A4: =Raw_Customers!A4 -> CUST1003 | B4: =Raw_Customers!B4 -> Ayaan Verma | C4: =PROPER(TRIM(Raw_Customers!C4)) -> Kolkata | D4: =Raw_Customers!D4 -> 2024-03-10 | E4: =Raw_Customers!E4 -> 21 | F4: =IF(TRIM(Raw_Customers!F4)="","Not Specified",TRIM(Raw_Customers!F4)) -> Not Specified
A5: =Raw_Customers!A5 -> CUST1004 | B5: =Raw_Customers!B5 -> Riya Sharma | C5: =PROPER(TRIM(Raw_Customers!C5)) -> Jaipur | D5: =Raw_Customers!D5 -> 2024-02-11 | E5: =Raw_Customers!E5 -> 21 | F5: =IF(TRIM(Raw_Customers!F5)="","Not Specified",TRIM(Raw_Customers!F5)) -> Female
A6: =Raw_Customers!A6 -> CUST1005 | B6: =Raw_Customers!B6 -> Ishaan Yadav | C6: =PROPER(TRIM(Raw_Customers!C6)) -> Mumbai | D6: =Raw_Customers!D6 -> 2023-05-01 | E6: =Raw_Customers!E6 -> 54 | F6: =IF(TRIM(Raw_Customers!F6)="","Not Specified",TRIM(Raw_Customers!F6)) -> Male
A7: =Raw_Customers!A7 -> CUST1006 | B7: =Raw_Customers!B7 -> Sai Verma | C7: =PROPER(TRIM(Raw_Customers!C7)) -> Jaipur | D7: =Raw_Customers!D7 -> 2023-07-12 | E7: =Raw_Customers!E7 -> 41 | F7: =IF(TRIM(Raw_Customers!F7)="","Not Specified",TRIM(Raw_Customers!F7)) -> Male
A8: =Raw_Customers!A8 -> CUST1007 | B8: =Raw_Customers!B8 -> Aditya Reddy | C8: =PROPER(TRIM(Raw_Customers!C8)) -> Bhopal | D8: =Raw_Customers!D8 -> 2023-07-30 | E8: =Raw_Customers!E8 -> 49 | F8: =IF(TRIM(Raw_Customers!F8)="","Not Specified",TRIM(Raw_Customers!F8)) -> Not Specified
A9: =Raw_Customers!A9 -> CUST1008 | B9: =Raw_Customers!B9 -> Ananya Mishra | C9: =PROPER(TRIM(Raw_Customers!C9)) -> Jaipur | D9: =Raw_Customers!D9 -> 2024-04-09 | E9: =Raw_Customers!E9 -> 41 | F9: =IF(TRIM(Raw_Customers!F9)="","Not Specified",TRIM(Raw_Customers!F9)) -> Male
A10: =Raw_Customers!A10 -> CUST1009 | B10: =Raw_Customers!B10 -> Sai Singh | C10: =PROPER(TRIM(Raw_Customers!C10)) -> Indore | D10: =Raw_Customers!D10 -> 2023-11-04 | E10: =Raw_Customers!E10 -> 51 | F10: =IF(TRIM(Raw_Customers!F10)="","Not Specified",TRIM(Raw_Customers!F10)) -> Female
A11: =Raw_Customers!A11 -> CUST1010 | B11: =Raw_Customers!B11 -> Kiara Gupta | C11: =PROPER(TRIM(Raw_Customers!C11)) -> Jaipur | D11: =Raw_Customers!D11 -> 2023-03-16 | E11: =Raw_Customers!E11 -> 25 | F11: =IF(TRIM(Raw_Customers!F11)="","Not Specified",TRIM(Raw_Customers!F11)) -> Not Specified
A12: =Raw_Customers!A12 -> CUST1011 | B12: =Raw_Customers!B12 -> Ananya Patel | C12: =PROPER(TRIM(Raw_Customers!C12)) -> Chennai | D12: =Raw_Customers!D12 -> 2024-03-07 | E12: =Raw_Customers!E12 -> 20 | F12: =IF(TRIM(Raw_Customers!F12)="","Not Specified",TRIM(Raw_Customers!F12)) -> Male
A13: =Raw_Customers!A13 -> CUST1012 | B13: =Raw_Customers!B13 -> Riya Kumar | C13: =PROPER(TRIM(Raw_Customers!C13)) -> Pune | D13: =Raw_Customers!D13 -> 2023-12-25 | E13: =Raw_Customers!E13 -> 49 | F13: =IF(TRIM(Raw_Customers!F13)="","Not Specified",TRIM(Raw_Customers!F13)) -> Not Specified
... A801: =Raw_Customers!A801 -> CUST1800 | B801: =Raw_Customers!B801 -> Ishaan Singh | C801: =PROPER(TRIM(Raw_Customers!C801)) -> Indore | D801: =Raw_Customers!D801 -> 2023-09-22 | E801: =Raw_Customers!E801 -> 35 | F801: =IF(TRIM(Raw_Customers!F801)="","Not Specified",TRIM(Raw_Customers!F801)) -> Male

Sheet Cleaned_Orders
A1: Order_ID | B1: Customer_ID | C1: Restaurant_ID | D1: Delivery_Partner_ID | E1: Order_Date | F1: Order_Value_Clean | G1: Status | H1: Delivery_Time_Min | I1: Customer_Rating | J1: Is_Duplicate | K1: Is_Value_Anomaly | L1: Restaurant_City
A2: =Raw_Orders!A2 -> 504897 | B2: =Raw_Orders!B2 -> CUST1333 | C2: =Raw_Orders!C2 -> REST296 | D2: =Raw_Orders!D2 -> DP317 | E2: =Raw_Orders!E2 -> 2024-04-06 | F2: =IF(Raw_Orders!F2<0,0,Raw_Orders!F2) -> 980.07 | G2: =Raw_Orders!G2 -> Delivered | H2: =IF(Raw_Orders!H2="","N/A",Raw_Orders!H2) -> 28.6 | I2: =IF(Raw_Orders!I2="","Not Rated",Raw_Orders!I2) -> 4.1 | J2: =IF(COUNTIF($A$2:A2,A2)>1,"Duplicate","Unique") -> Unique | K2: =IF(Raw_Orders!F2<0,"Anomaly","OK") -> OK | L2: =IFERROR(VLOOKUP(C2,Raw_Restaurants!$A$2:$C$151,3,FALSE()),"Unknown") -> Chennai
A3: =Raw_Orders!A3 -> 503302 | B3: =Raw_Orders!B3 -> CUST1109 | C3: =Raw_Orders!C3 -> REST274 | D3: =Raw_Orders!D3 -> DP490 | E3: =Raw_Orders!E3 -> 2024-04-12 | F3: =IF(Raw_Orders!F3<0,0,Raw_Orders!F3) -> 1123.98 | G3: =Raw_Orders!G3 -> Delivered | H3: =IF(Raw_Orders!H3="","N/A",Raw_Orders!H3) -> 70.9 | I3: =IF(Raw_Orders!I3="","Not Rated",Raw_Orders!I3) -> 2.8 | J3: =IF(COUNTIF($A$2:A3,A3)>1,"Duplicate","Unique") -> Unique | K3: =IF(Raw_Orders!F3<0,"Anomaly","OK") -> OK | L3: =IFERROR(VLOOKUP(C3,Raw_Restaurants!$A$2:$C$151,3,FALSE()),"Unknown") -> Chennai
A4: =Raw_Orders!A4 -> 501846 | B4: =Raw_Orders!B4 -> CUST1340 | C4: =Raw_Orders!C4 -> REST300 | D4: =Raw_Orders!D4 -> DP426 | E4: =Raw_Orders!E4 -> 2024-07-30 | F4: =IF(Raw_Orders!F4<0,0,Raw_Orders!F4) -> 125.1 | G4: =Raw_Orders!G4 -> Delivered | H4: =IF(Raw_Orders!H4="","N/A",Raw_Orders!H4) -> 70.6 | I4: =IF(Raw_Orders!I4="","Not Rated",Raw_Orders!I4) -> 4.6 | J4: =IF(COUNTIF($A$2:A4,A4)>1,"Duplicate","Unique") -> Unique | K4: =IF(Raw_Orders!F4<0,"Anomaly","OK") -> OK | L4: =IFERROR(VLOOKUP(C4,Raw_Restaurants!$A$2:$C$151,3,FALSE()),"Unknown") -> Indore
A5: =Raw_Orders!A5 -> 500862 | B5: =Raw_Orders!B5 -> CUST1260 | C5: =Raw_Orders!C5 -> REST265 | D5: =Raw_Orders!D5 -> DP455 | E5: =Raw_Orders!E5 -> 2024-11-13 | F5: =IF(Raw_Orders!F5<0,0,Raw_Orders!F5) -> 227.97 | G5: =Raw_Orders!G5 -> Delivered | H5: =IF(Raw_Orders!H5="","N/A",Raw_Orders!H5) -> 38.6 | I5: =IF(Raw_Orders!I5="","Not Rated",Raw_Orders!I5) -> 2.9 | J5: =IF(COUNTIF($A$2:A5,A5)>1,"Duplicate","Unique") -> Unique | K5: =IF(Raw_Orders!F5<0,"Anomaly","OK") -> OK | L5: =IFERROR(VLOOKUP(C5,Raw_Restaurants!$A$2:$C$151,3,FALSE()),"Unknown") -> Bhopal
A6: =Raw_Orders!A6 -> 501267 | B6: =Raw_Orders!B6 -> CUST1349 | C6: =Raw_Orders!C6 -> REST250 | D6: =Raw_Orders!D6 -> DP415 | E6: =Raw_Orders!E6 -> 2024-03-07 | F6: =IF(Raw_Orders!F6<0,0,Raw_Orders!F6) -> 700.67 | G6: =Raw_Orders!G6 -> Delivered | H6: =IF(Raw_Orders!H6="","N/A",Raw_Orders!H6) -> 23.6 | I6: =IF(Raw_Orders!I6="","Not Rated",Raw_Orders!I6) -> 4 | J6: =IF(COUNTIF($A$2:A6,A6)>1,"Duplicate","Unique") -> Unique | K6: =IF(Raw_Orders!F6<0,"Anomaly","OK") -> OK | L6: =IFERROR(VLOOKUP(C6,Raw_Restaurants!$A$2:$C$151,3,FALSE()),"Unknown") -> Delhi
A7: =Raw_Orders!A7 -> 500854 | B7: =Raw_Orders!B7 -> CUST1409 | C7: =Raw_Orders!C7 -> REST228 | D7: =Raw_Orders!D7 -> DP403 | E7: =Raw_Orders!E7 -> 2024-08-27 | F7: =IF(Raw_Orders!F7<0,0,Raw_Orders!F7) -> 293.42 | G7: =Raw_Orders!G7 -> Cancelled | H7: =IF(Raw_Orders!H7="","N/A",Raw_Orders!H7) -> N/A | I7: =IF(Raw_Orders!I7="","Not Rated",Raw_Orders!I7) -> Not Rated | J7: =IF(COUNTIF($A$2:A7,A7)>1,"Duplicate","Unique") -> Unique | K7: =IF(Raw_Orders!F7<0,"Anomaly","OK") -> OK | L7: =IFERROR(VLOOKUP(C7,Raw_Restaurants!$A$2:$C$151,3,FALSE()),"Unknown") -> Pune
A8: =Raw_Orders!A8 -> 504744 | B8: =Raw_Orders!B8 -> CUST1775 | C8: =Raw_Orders!C8 -> REST238 | D8: =Raw_Orders!D8 -> DP450 | E8: =Raw_Orders!E8 -> 2024-06-13 | F8: =IF(Raw_Orders!F8<0,0,Raw_Orders!F8) -> 372.71 | G8: =Raw_Orders!G8 -> Delivered | H8: =IF(Raw_Orders!H8="","N/A",Raw_Orders!H8) -> 38.5 | I8: =IF(Raw_Orders!I8="","Not Rated",Raw_Orders!I8) -> 4.1 | J8: =IF(COUNTIF($A$2:A8,A8)>1,"Duplicate","Unique") -> Unique | K8: =IF(Raw_Orders!F8<0,"Anomaly","OK") -> OK | L8: =IFERROR(VLOOKUP(C8,Raw_Restaurants!$A$2:$C$151,3,FALSE()),"Unknown") -> Chennai
A9: =Raw_Orders!A9 -> 502221 | B9: =Raw_Orders!B9 -> CUST1596 | C9: =Raw_Orders!C9 -> REST213 | D9: =Raw_Orders!D9 -> DP452 | E9: =Raw_Orders!E9 -> 2024-03-26 | F9: =IF(Raw_Orders!F9<0,0,Raw_Orders!F9) -> 753.82 | G9: =Raw_Orders!G9 -> Delivered | H9: =IF(Raw_Orders!H9="","N/A",Raw_Orders!H9) -> 49 | I9: =IF(Raw_Orders!I9="","Not Rated",Raw_Orders!I9) -> 4.2 | J9: =IF(COUNTIF($A$2:A9,A9)>1,"Duplicate","Unique") -> Unique | K9: =IF(Raw_Orders!F9<0,"Anomaly","OK") -> OK | L9: =IFERROR(VLOOKUP(C9,Raw_Restaurants!$A$2:$C$151,3,FALSE()),"Unknown") -> Pune
A10: =Raw_Orders!A10 -> 502705 | B10: =Raw_Orders!B10 -> CUST1598 | C10: =Raw_Orders!C10 -> REST326 | D10: =Raw_Orders!D10 -> DP390 | E10: =Raw_Orders!E10 -> 2024-03-27 | F10: =IF(Raw_Orders!F10<0,0,Raw_Orders!F10) -> 1393.56 | G10: =Raw_Orders!G10 -> Delivered | H10: =IF(Raw_Orders!H10="","N/A",Raw_Orders!H10) -> 51.6 | I10: =IF(Raw_Orders!I10="","Not Rated",Raw_Orders!I10) -> 3.9 | J10: =IF(COUNTIF($A$2:A10,A10)>1,"Duplicate","Unique") -> Unique | K10: =IF(Raw_Orders!F10<0,"Anomaly","OK") -> OK | L10: =IFERROR(VLOOKUP(C10,Raw_Restaurants!$A$2:$C$151,3,FALSE()),"Unknown") -> Bhopal
A11: =Raw_Orders!A11 -> 504378 | B11: =Raw_Orders!B11 -> CUST1714 | C11: =Raw_Orders!C11 -> REST283 | D11: =Raw_Orders!D11 -> DP434 | E11: =Raw_Orders!E11 -> 2024-05-27 | F11: =IF(Raw_Orders!F11<0,0,Raw_Orders!F11) -> 821.27 | G11: =Raw_Orders!G11 -> Delivered | H11: =IF(Raw_Orders!H11="","N/A",Raw_Orders!H11) -> 70.9 | I11: =IF(Raw_Orders!I11="","Not Rated",Raw_Orders!I11) -> 4.5 | J11: =IF(COUNTIF($A$2:A11,A11)>1,"Duplicate","Unique") -> Unique | K11: =IF(Raw_Orders!F11<0,"Anomaly","OK") -> OK | L11: =IFERROR(VLOOKUP(C11,Raw_Restaurants!$A$2:$C$151,3,FALSE()),"Unknown") -> Delhi
A12: =Raw_Orders!A12 -> 504759 | B12: =Raw_Orders!B12 -> CUST1151 | C12: =Raw_Orders!C12 -> REST294 | D12: =Raw_Orders!D12 -> DP328 | E12: =Raw_Orders!E12 -> 2024-07-31 | F12: =IF(Raw_Orders!F12<0,0,Raw_Orders!F12) -> 0 | G12: =Raw_Orders!G12 -> Delivered | H12: =IF(Raw_Orders!H12="","N/A",Raw_Orders!H12) -> 46.9 | I12: =IF(Raw_Orders!I12="","Not Rated",Raw_Orders!I12) -> 3.9 | J12: =IF(COUNTIF($A$2:A12,A12)>1,"Duplicate","Unique") -> Unique | K12: =IF(Raw_Orders!F12<0,"Anomaly","OK") -> Anomaly | L12: =IFERROR(VLOOKUP(C12,Raw_Restaurants!$A$2:$C$151,3,FALSE()),"Unknown") -> Hyderabad
A13: =Raw_Orders!A13 -> 504487 | B13: =Raw_Orders!B13 -> CUST1410 | C13: =Raw_Orders!C13 -> REST330 | D13: =Raw_Orders!D13 -> DP408 | E13: =Raw_Orders!E13 -> 2024-09-21 | F13: =IF(Raw_Orders!F13<0,0,Raw_Orders!F13) -> 153.43 | G13: =Raw_Orders!G13 -> Delivered | H13: =IF(Raw_Orders!H13="","N/A",Raw_Orders!H13) -> 22.2 | I13: =IF(Raw_Orders!I13="","Not Rated",Raw_Orders!I13) -> Not Rated | J13: =IF(COUNTIF($A$2:A13,A13)>1,"Duplicate","Unique") -> Unique | K13: =IF(Raw_Orders!F13<0,"Anomaly","OK") -> OK | L13: =IFERROR(VLOOKUP(C13,Raw_Restaurants!$A$2:$C$151,3,FALSE()),"Unknown") -> Hyderabad
... A5081: =Raw_Orders!A5081 -> 503551 | B5081: =Raw_Orders!B5081 -> CUST1379 | C5081: =Raw_Orders!C5081 -> REST258 | D5081: =Raw_Orders!D5081 -> DP429 | E5081: =Raw_Orders!E5081 -> 2024-08-14 | F5081: =IF(Raw_Orders!F5081<0,0,Raw_Orders!F5081) -> 780.66 | G5081: =Raw_Orders!G5081 -> Delivered | H5081: =IF(Raw_Orders!H5081="","N/A",Raw_Orders!H5081) -> 55.2 | I5081: =IF(Raw_Orders!I5081="","Not Rated",Raw_Orders!I5081) -> 3.9 | J5081: =IF(COUNTIF($A$2:A5081,A5081)>1,"Duplicate","Unique") -> Unique | K5081: =IF(Raw_Orders!F5081<0,"Anomaly","OK") -> OK | L5081: =IFERROR(VLOOKUP(C5081,Raw_Restaurants!$A$2:$C$151,3,FALSE()),"Unknown") -> Mumbai

Sheet Excel_Summary
A1: FOOD DELIVERY - EXCEL CLEANING SUMMARY
A3: Metric | B3: Value
A4: Total Orders (Raw) | B4: =COUNTA(Raw_Orders!A2:A5081) -> 5080
A5: Duplicate Orders Found | B5: =COUNTIF(Cleaned_Orders!J2:J5081,"Duplicate") -> 80
A6: Negative/Anomalous Order Values | B6: =COUNTIF(Cleaned_Orders!K2:K5081,"Anomaly") -> 83
A7: Missing Delivery Time | B7: =COUNTIF(Cleaned_Orders!H2:H5081,"N/A") -> 840
A8: Missing Customer Rating | B8: =COUNTIF(Cleaned_Orders!I2:I5081,"Not Rated") -> 1155
A9: Cancelled Orders | B9: =COUNTIF(Cleaned_Orders!G2:G5081,"Cancelled") -> 589
A10: Delivered Orders | B10: =COUNTIF(Cleaned_Orders!G2:G5081,"Delivered") -> 4082
A11: Delayed Orders | B11: =COUNTIF(Cleaned_Orders!G2:G5081,"Delayed") -> 409
A12: Overall Cancellation Rate % | B12: =ROUND(COUNTIF(Cleaned_Orders!G2:G5081,"Cancelled")/COUNTA(Cleaned_Orders!G2:G5081)*100,2) -> 11.59
A13: Average Order Value (cleaned) | B13: =ROUND(AVERAGE(Cleaned_Orders!F2:F5081),2) -> 744.28
A14: Total Revenue (Delivered only) | B14: =ROUND(SUMIF(Cleaned_Orders!G2:G5081,"Delivered",Cleaned_Orders!F2:F5081),2) -> 3040609.9
A16: CITY-WISE ANALYSIS (via Restaurant city lookup)
A18: City | B18: Total Orders | C18: Cancelled Orders | D18: Cancellation Rate % | E18: Avg Order Value
A19: Bangalore | B19: =COUNTIFS(Cleaned_Orders!$L$2:$L$5081,A19) -> 381 | C19: =COUNTIFS(Cleaned_Orders!$L$2:$L$5081,A19,Cleaned_Orders!$G$2:$G$5081,"Cancelled") -> 49 | D19: =IFERROR(ROUND(C19/B19*100,2),0) -> 12.86 | E19: =IFERROR(ROUND(AVERAGEIFS(Cleaned_Orders!$F$2:$F$5081,Cleaned_Orders!$L$2:$L$5081,A19),2),0) -> 760.44
A20: Bhopal | B20: =COUNTIFS(Cleaned_Orders!$L$2:$L$5081,A20) -> 558 | C20: =COUNTIFS(Cleaned_Orders!$L$2:$L$5081,A20,Cleaned_Orders!$G$2:$G$5081,"Cancelled") -> 77 | D20: =IFERROR(ROUND(C20/B20*100,2),0) -> 13.8 | E20: =IFERROR(ROUND(AVERAGEIFS(Cleaned_Orders!$F$2:$F$5081,Cleaned_Orders!$L$2:$L$5081,A20),2),0) -> 740.1
A21: Chennai | B21: =COUNTIFS(Cleaned_Orders!$L$2:$L$5081,A21) -> 475 | C21: =COUNTIFS(Cleaned_Orders!$L$2:$L$5081,A21,Cleaned_Orders!$G$2:$G$5081,"Cancelled") -> 50 | D21: =IFERROR(ROUND(C21/B21*100,2),0) -> 10.53 | E21: =IFERROR(ROUND(AVERAGEIFS(Cleaned_Orders!$F$2:$F$5081,Cleaned_Orders!$L$2:$L$5081,A21),2),0) -> 754.33
A22: Delhi | B22: =COUNTIFS(Cleaned_Orders!$L$2:$L$5081,A22) -> 566 | C22: =COUNTIFS(Cleaned_Orders!$L$2:$L$5081,A22,Cleaned_Orders!$G$2:$G$5081,"Cancelled") -> 58 | D22: =IFERROR(ROUND(C22/B22*100,2),0) -> 10.25 | E22: =IFERROR(ROUND(AVERAGEIFS(Cleaned_Orders!$F$2:$F$5081,Cleaned_Orders!$L$2:$L$5081,A22),2),0) -> 747.69
A23: Hyderabad | B23: =COUNTIFS(Cleaned_Orders!$L$2:$L$5081,A23) -> 502 | C23: =COUNTIFS(Cleaned_Orders!$L$2:$L$5081,A23,Cleaned_Orders!$G$2:$G$5081,"Cancelled") -> 49 | D23: =IFERROR(ROUND(C23/B23*100,2),0) -> 9.76 | E23: =IFERROR(ROUND(AVERAGEIFS(Cleaned_Orders!$F$2:$F$5081,Cleaned_Orders!$L$2:$L$5081,A23),2),0) -> 726.19
A24: Indore | B24: =COUNTIFS(Cleaned_Orders!$L$2:$L$5081,A24) -> 590 | C24: =COUNTIFS(Cleaned_Orders!$L$2:$L$5081,A24,Cleaned_Orders!$G$2:$G$5081,"Cancelled") -> 73 | D24: =IFERROR(ROUND(C24/B24*100,2),0) -> 12.37 | E24: =IFERROR(ROUND(AVERAGEIFS(Cleaned_Orders!$F$2:$F$5081,Cleaned_Orders!$L$2:$L$5081,A24),2),0) -> 715.3
A25: Jaipur | B25: =COUNTIFS(Cleaned_Orders!$L$2:$L$5081,A25) -> 496 | C25: =COUNTIFS(Cleaned_Orders!$L$2:$L$5081,A25,Cleaned_Orders!$G$2:$G$5081,"Cancelled") -> 66 | D25: =IFERROR(ROUND(C25/B25*100,2),0) -> 13.31 | E25: =IFERROR(ROUND(AVERAGEIFS(Cleaned_Orders!$F$2:$F$5081,Cleaned_Orders!$L$2:$L$5081,A25),2),0) -> 726.34
A26: Kolkata | B26: =COUNTIFS(Cleaned_Orders!$L$2:$L$5081,A26) -> 467 | C26: =COUNTIFS(Cleaned_Orders!$L$2:$L$5081,A26,Cleaned_Orders!$G$2:$G$5081,"Cancelled") -> 44 | D26: =IFERROR(ROUND(C26/B26*100,2),0) -> 9.42 | E26: =IFERROR(ROUND(AVERAGEIFS(Cleaned_Orders!$F$2:$F$5081,Cleaned_Orders!$L$2:$L$5081,A26),2),0) -> 774.08
A27: Mumbai | B27: =COUNTIFS(Cleaned_Orders!$L$2:$L$5081,A27) -> 520 | C27: =COUNTIFS(Cleaned_Orders!$L$2:$L$5081,A27,Cleaned_Orders!$G$2:$G$5081,"Cancelled") -> 65 | D27: =IFERROR(ROUND(C27/B27*100,2),0) -> 12.5 | E27: =IFERROR(ROUND(AVERAGEIFS(Cleaned_Orders!$F$2:$F$5081,Cleaned_Orders!$L$2:$L$5081,A27),2),0) -> 756.2
A28: Pune | B28: =COUNTIFS(Cleaned_Orders!$L$2:$L$5081,A28) -> 525 | C28: =COUNTIFS(Cleaned_Orders!$L$2:$L$5081,A28,Cleaned_Orders!$G$2:$G$5081,"Cancelled") -> 58 | D28: =IFERROR(ROUND(C28/B28*100,2),0) -> 11.05 | E28: =IFERROR(ROUND(AVERAGEIFS(Cleaned_Orders!$F$2:$F$5081,Cleaned_Orders!$L$2:$L$5081,A28),2),0) -> 752.71
